{
  "$schema":"https://json-schema.org/draft/2020-12/schema",
  "$id":"urn:ptah:schema:domain:disk-partition-table:0.1.0",
  "title":"Ptah Disk Partition Table Revision",
  "x-ptah-schema-name":"domain.disk-partition-table","x-ptah-schema-version":"0.1.0","x-ptah-maturity":"candidate",
  "type":"object","additionalProperties":false,
  "required":["envelope","disk_image_revision_ref","table_revision_number","scheme","sector_size","table_ranges","partition_refs","pack_revision_ref","validation_results","generated_at","evidence_refs","extensions"],
  "properties":{
    "envelope":{"allOf":[{"$ref":"urn:ptah:schema:common:entity-envelope:0.1.0"},{"properties":{"entity_kind":{"const":"disk.partition_table"}}}]},"disk_image_revision_ref":{"$ref":"urn:ptah:schema:common:definitions:0.1.0#/$defs/entityRef"},"table_revision_number":{"$ref":"urn:ptah:schema:common:definitions:0.1.0#/$defs/positiveInteger"},"parent_table_refs":{"type":"array","items":{"$ref":"urn:ptah:schema:common:definitions:0.1.0#/$defs/entityRef"},"uniqueItems":true},"scheme":{"type":"string","enum":["gpt","mbr","hybrid_mbr_gpt","android_dynamic_partitions","apple_partition_map","vendor_table","none","unknown","other_registered"]},"scheme_version":{"type":"string","maxLength":128},"sector_size":{"type":"integer","minimum":1},"table_ranges":{"type":"array","minItems":1,"items":{"$ref":"urn:ptah:schema:domain:definitions:0.1.0#/$defs/byteRange"}},"primary_copy_ref":{"$ref":"urn:ptah:schema:common:definitions:0.1.0#/$defs/entityRef"},"backup_copy_ref":{"$ref":"urn:ptah:schema:common:definitions:0.1.0#/$defs/entityRef"},"partition_refs":{"type":"array","items":{"$ref":"urn:ptah:schema:common:definitions:0.1.0#/$defs/entityRef"},"uniqueItems":true},"pack_revision_ref":{"$ref":"urn:ptah:schema:common:definitions:0.1.0#/$defs/entityRef"},"validation_results":{"type":"array","minItems":1,"items":{"type":"object","additionalProperties":false,"required":["check","result"],"properties":{"check":{"type":"string","enum":["header_signature","header_crc","entry_crc","backup_consistency","bounds","alignment","overlap","duplicate_guid","logical_extent_consistency","other_registered"]},"result":{"type":"string","enum":["passed","passed_with_warnings","failed","not_applicable","inconclusive"]},"evidence_refs":{"type":"array","items":{"$ref":"urn:ptah:schema:common:definitions:0.1.0#/$defs/entityRef"},"uniqueItems":true},"details":{"type":"string","maxLength":4096}}}},"generated_at":{"$ref":"urn:ptah:schema:common:definitions:0.1.0#/$defs/utcDateTime"},"evidence_refs":{"type":"array","minItems":1,"items":{"$ref":"urn:ptah:schema:common:definitions:0.1.0#/$defs/entityRef"},"uniqueItems":true},"limitations":{"type":"array","items":{"type":"string","minLength":1,"maxLength":4096}},"extensions":{"$ref":"urn:ptah:schema:common:definitions:0.1.0#/$defs/extensions"}
  }
}