{"suite_id":"ptah.conformance.application-browser-semantic-shell.0.1.0","fixture_version":"0.1.0","fixture_class":"cross_record_scenarios","execution_status":"specification_only_until_wp13","cases":[{"id":"A01_VALID_APPLICATION_REVISION_COMPATIBILITY","expected":"valid","setup":"Stable Application uses one immutable Revision and exact target Compatibility before Installation.","assertions":["identity stable","Revision immutable","Compatibility directional"]},{"id":"A02_INVALID_PATH_AS_APPLICATION_ID","expected":"invalid","expected_code":"APPLICATION_ALIAS_NOT_CANONICAL","setup":"Executable path or package ID becomes canonical Application identity.","assertions":["scoped Alias required"]},{"id":"A03_VALID_INSTALL_ACK_THEN_VERIFY","expected":"valid","setup":"Provider acknowledges install, then exact installed Revision/files/configuration are read back.","assertions":["installed_unverified before verification","installed_verified after proof"]},{"id":"A04_INVALID_INSTALL_ACK_AS_VERIFIED","expected":"invalid","expected_code":"INSTALL_ACK_NOT_VERIFICATION","setup":"Backend exit code marks installation verified without read-back.","assertions":["verification required"]},{"id":"A05_VALID_NEW_INSTALL_RETRY","expected":"valid","setup":"Transient install failure retries with same logical Operation and a new Attempt/nonce.","assertions":["Attempt not reused","Receipts retained"]},{"id":"A06_INVALID_INSTALL_ATTEMPT_REUSE","expected":"invalid","expected_code":"INSTALL_RETRY_REUSES_ATTEMPT","setup":"Installation retry reuses previous Attempt identity.","assertions":["new Attempt required"]},{"id":"A07_VALID_SESSION_WITHOUT_WINDOW","expected":"valid","setup":"Headless Application Session is running without a Window or Display.","assertions":["session functional scope explicit","display optional"]},{"id":"A08_INVALID_WINDOW_VISIBLE_AS_READY","expected":"invalid","expected_code":"WINDOW_VISIBILITY_NOT_APPLICATION_READINESS","setup":"Visible Window alone marks Application Session ready.","assertions":["functional readiness evidence required"]},{"id":"A09_VALID_DISPLAY_DEGRADATION","expected":"valid","setup":"Display Session fails while headless Application Session continues.","assertions":["degradation scoped","session not falsely failed"]},{"id":"A10_INVALID_PROVIDER_RESTART_CONTINUITY","expected":"invalid","expected_code":"APPLICATION_PROVIDER_GENERATION_STALE","setup":"Application Session continues silently after Provider restart using old Process/Window context.","assertions":["new generation and verification required"]},{"id":"A11_VALID_WINDOW_RECREATION","expected":"valid","setup":"Application Session survives Window recreation with a new Window identity/generation.","assertions":["Session stable","old Window retained"]},{"id":"A12_VALID_APPLICATION_CHECKPOINT","expected":"valid","setup":"Application checkpoint component references WP05 Checkpoint Bundle and exact Session/Process/window state.","assertions":["checkpoint not recovery proof"]},{"id":"A13_INVALID_CHECKPOINT_AS_RECOVERY","expected":"invalid","expected_code":"APPLICATION_CHECKPOINT_NOT_RECOVERY","setup":"Hash-verified checkpoint is treated as functional recovery.","assertions":["new generation Recovery Verification required"]},{"id":"A14_VALID_RECOVERY_VERIFIED","expected":"valid","setup":"Restore creates new Process/Window/Display generation and verifies required functional postconditions.","assertions":["old state retained","new Recovery Verification"]},{"id":"A15_VALID_RECOVERY_LIMITED","expected":"valid","setup":"Application files and Process restore but one service/data function remains unavailable.","assertions":["recovered_with_limitations","no full success"]},{"id":"A16_INVALID_DISPLAY_PIXELS_AS_RECOVERY","expected":"invalid","expected_code":"DISPLAY_RESTORED_NOT_APPLICATION_RECOVERED","setup":"Pixels stream after restore but application function is unverified.","assertions":["functional checks required"]},{"id":"A17_INVALID_STALE_WINDOW_HANDLE","expected":"invalid","expected_code":"WINDOW_HANDLE_STALE","setup":"Old backend window handle is used after recreation/Provider generation change.","assertions":["fresh Window identity/observation required"]},{"id":"A18_VALID_UNINSTALL_VERIFIED","expected":"valid","setup":"Uninstall verifies application state and required remnants absent.","assertions":["cleanup verified","history retained"]},{"id":"A19_INVALID_UNINSTALL_ACK_AS_ABSENCE","expected":"invalid","expected_code":"UNINSTALL_ACK_NOT_ABSENCE_PROOF","setup":"Uninstall command success is treated as verified absence.","assertions":["read-back required"]},{"id":"A20_VALID_BACKEND_APPLICATION_REPLACEMENT","expected":"valid","setup":"Native/VM/container application Provider changes.","assertions":["Application identity stable","new Compatibility/Installation/Session/Attempts"]},{"id":"B01_VALID_BINARY_REVISION","expected":"valid","setup":"Browser Binary role references immutable exact Binary Revision.","assertions":["path not identity","digest/toolchain exact"]},{"id":"B02_INVALID_PID_AS_BROWSER_PROCESS_ID","expected":"invalid","expected_code":"BROWSER_PID_NOT_CANONICAL","setup":"OS PID or CDP endpoint becomes canonical Browser Process identity.","assertions":["runtime.process and Browser Process required"]},{"id":"B03_VALID_PROFILE_PERSISTS_RESTART","expected":"valid","setup":"Persistent Profile identity/revision survives Browser Process restart.","assertions":["new Process generation","Profile stable"]},{"id":"B04_INVALID_UNTRUSTED_WRITABLE_PROFILE_SHARE","expected":"invalid","expected_code":"WRITABLE_PROFILE_ISOLATION_VIOLATION","setup":"Mutually untrusted Workspaces concurrently write one Profile.","assertions":["exclusive/serialized Lease required"]},{"id":"B05_VALID_SHARED_READONLY_PROFILE","expected":"valid","setup":"Multiple Contexts read one verified Profile Revision with writes disabled.","assertions":["shared_readonly enforced"]},{"id":"B06_INVALID_EXPIRED_PROFILE_FENCE","expected":"invalid","expected_code":"BROWSER_PROFILE_FENCE_STALE","setup":"Context writes after Profile Lease/fence expires.","assertions":["write blocked"]},{"id":"B07_VALID_CONTEXT_ISOLATION","expected":"valid","setup":"Context binds explicit profile/storage/network/permission policy and generation.","assertions":["isolation explicit"]},{"id":"B08_INVALID_BACKEND_INCOGNITO_ASSUMPTION","expected":"invalid","expected_code":"BROWSER_PRIVACY_MODE_UNPROVEN","setup":"One backend flag is treated as complete ephemeral/privacy proof.","assertions":["storage/retention/privacy verification required"]},{"id":"B09_VALID_PAGE_FRAME_HIERARCHY","expected":"valid","setup":"Page contains same-origin and cross-origin Frames with separate identities.","assertions":["Frame identity distinct","origin limitations retained"]},{"id":"B10_INVALID_TARGET_ID_AS_PAGE_ID","expected":"invalid","expected_code":"BROWSER_TARGET_ALIAS_NOT_PAGE_IDENTITY","setup":"CDP/WebDriver target ID becomes canonical Page identity.","assertions":["scoped Alias only"]},{"id":"B11_VALID_POPUP_RELATIONSHIP","expected":"valid","setup":"Popup links opener Page and new Page while preserving both identities.","assertions":["relationship not identity replacement"]},{"id":"B12_INVALID_POPUP_REUSES_OPENER_ID","expected":"invalid","expected_code":"BROWSER_POPUP_PAGE_IDENTITY_COLLAPSE","setup":"Popup overwrites opener Page identity.","assertions":["new Page identity required"]},{"id":"B13_VALID_NAVIGATION_SEQUENCE","expected":"valid","setup":"Same Page records multiple immutable Navigation revisions including same-document change.","assertions":["Page stable","sequence exact"]},{"id":"B14_INVALID_URL_AS_NAVIGATION_ID","expected":"invalid","expected_code":"URL_NOT_NAVIGATION_IDENTITY","setup":"URL string replaces Page/Navigation identity.","assertions":["Navigation record required"]},{"id":"B15_VALID_CHALLENGE_PAUSES_PAGE","expected":"valid","setup":"MFA/captcha/consent Challenge pauses only affected Page while Process/other Pages remain active.","assertions":["scope limited","automation fenced"]},{"id":"B16_INVALID_CHALLENGE_SOLVED_BY_SECRET_EXPORT","expected":"invalid","expected_code":"CHALLENGE_SECRET_EXPORT_PROHIBITED","setup":"Credentials/MFA secret is copied into public evidence to resolve Challenge.","assertions":["secret reference/private flow required"]},{"id":"B17_VALID_HUMAN_CHALLENGE_COMPLETION","expected":"valid","setup":"Control transfers to human, automation is fenced, and fresh evidence proves Challenge resolved.","assertions":["Lease/fence changed","no secret disclosure"]},{"id":"B18_INVALID_CHALLENGE_FAILURE_KILLS_PROCESS","expected":"invalid","expected_code":"BROWSER_CHALLENGE_SCOPE_COLLAPSE","setup":"One Page challenge marks entire Browser Process failed.","assertions":["scope-specific state required"]},{"id":"B19_VALID_DOWNLOAD_PIPELINE","expected":"valid","setup":"Browser Download initiates WP06 Transfer; digest, Content/Object and Location verify before completion.","assertions":["bytes accepted through WP06/WP03"]},{"id":"B20_INVALID_BROWSER_DOWNLOAD_COMPLETE_ONLY","expected":"invalid","expected_code":"BROWSER_DOWNLOAD_ACK_NOT_OBJECT_TRUTH","setup":"Browser event alone marks download completed_verified.","assertions":["Transfer/Object verification required"]},{"id":"B21_VALID_INTERRUPTED_DOWNLOAD_RESUME","expected":"valid","setup":"Download resumes with exact validators and new Transfer Attempt.","assertions":["partial bytes retained","new Attempt"]},{"id":"B22_INVALID_DOWNLOAD_PATH_AS_OBJECT_ID","expected":"invalid","expected_code":"DOWNLOAD_PATH_NOT_OBJECT_IDENTITY","setup":"Temporary download path becomes Object identity.","assertions":["Content/Object registration required"]},{"id":"B23_VALID_EVIDENCE_DISAGREEMENT","expected":"valid","setup":"DOM says button enabled while pixels/accessibility indicate disabled/covered.","assertions":["all evidence retained","no universal source assumed"]},{"id":"B24_INVALID_SCREENSHOT_AS_UNIVERSAL_TRUTH","expected":"invalid","expected_code":"BROWSER_EVIDENCE_CLASS_OVERCLAIM","setup":"Screenshot alone proves DOM/network/application state.","assertions":["bounded claim required"]},{"id":"B25_VALID_BROWSER_CHECKPOINT_RESTORE","expected":"valid","setup":"Profile/navigation checkpoint restores into new Process/Context/Page generations.","assertions":["old handles invalid","new recovery verification"]},{"id":"B26_INVALID_RESTORED_COOKIE_AS_AUTH_VALID","expected":"invalid","expected_code":"RESTORED_PROFILE_NOT_AUTHENTICATION_PROOF","setup":"Cookie presence after restore proves authenticated session.","assertions":["live auth verification required"]},{"id":"B27_VALID_WARM_POOL_REPLACEMENT","expected":"valid","setup":"Browser Provider/warm pool changes while stable Binary/Profile identity and evidence history remain.","assertions":["new Process/Context/Page generations"]},{"id":"S01_VALID_SEMANTIC_CONTEXT","expected":"valid","setup":"Semantic Context binds exact Application/Browser/Device surface and Provider generation.","assertions":["observation/mutation scopes explicit"]},{"id":"S02_INVALID_ELEMENT_HANDLE_AS_TARGET","expected":"invalid","expected_code":"SEMANTIC_BACKEND_HANDLE_NOT_TARGET_IDENTITY","setup":"Backend element handle becomes durable Target identity.","assertions":["Selector/Target/Target Result separation required"]},{"id":"S03_VALID_SNAPSHOT_NODE_TREE","expected":"valid","setup":"Immutable Snapshot and Node Snapshots retain role/name/state/relation/geometry under one generation.","assertions":["snapshot immutable","completeness explicit"]},{"id":"S04_VALID_PARTIAL_SEMANTIC_TREE","expected":"valid","setup":"Opaque cross-origin/custom canvas region makes Snapshot partial.","assertions":["partial retained","unknown scope explicit"]},{"id":"S05_INVALID_PARTIAL_AS_COMPLETE","expected":"invalid","expected_code":"SEMANTIC_COMPLETENESS_OVERCLAIM","setup":"Partial tree is labelled complete.","assertions":["correct completeness required"]},{"id":"S06_VALID_EVENT_INVALIDATION","expected":"valid","setup":"Semantic Event invalidates current Snapshot/Target Result after tree/focus/navigation change.","assertions":["reacquisition required"]},{"id":"S07_INVALID_STALE_TARGET_RESULT","expected":"invalid","expected_code":"SEMANTIC_TARGET_STALE","setup":"Action uses Target Result from old Snapshot/context/provider generation.","assertions":["fresh Target Result required"]},{"id":"S08_INVALID_AMBIGUOUS_TARGET","expected":"invalid","expected_code":"SEMANTIC_TARGET_AMBIGUOUS","setup":"Selector matches two enabled Submit buttons while policy requires unique.","assertions":["block or human select"]},{"id":"S09_VALID_RANKED_TARGET_WITH_POLICY","expected":"valid","setup":"Multiple matches are ranked and policy explicitly permits ranked multiple selection with evidence.","assertions":["ambiguity score/evidence retained"]},{"id":"S10_INVALID_FIRST_MATCH_SHORTCUT","expected":"invalid","expected_code":"SEMANTIC_FIRST_MATCH_PROHIBITED","setup":"Ambiguous selector silently chooses first backend match.","assertions":["explicit policy required"]},{"id":"S11_VALID_ACTION_ATTEMPT","expected":"valid","setup":"Action Attempt binds fresh Target Result, current Lease/fence, Provider generation and new WP02 Attempt.","assertions":["exact correlation"]},{"id":"S12_INVALID_ACTION_WITHOUT_CONTROL","expected":"invalid","expected_code":"SEMANTIC_CONTROL_AUTHORITY_MISSING","setup":"Automation mutates UI without current runtime.lease/fence.","assertions":["blocked"]},{"id":"S13_INVALID_ACTION_ATTEMPT_REUSE","expected":"invalid","expected_code":"SEMANTIC_ACTION_RETRY_REUSES_ATTEMPT","setup":"Action retry reuses prior WP02 Attempt/nonce.","assertions":["new Attempt required"]},{"id":"S14_VALID_PROVIDER_ACK_THEN_VERIFY","expected":"valid","setup":"Provider acknowledges click; fresh Snapshot/API/visual evidence verifies intended postcondition.","assertions":["ACK separate","Action Result verified"]},{"id":"S15_INVALID_ACK_AS_ACTION_SUCCESS","expected":"invalid","expected_code":"SEMANTIC_ACK_NOT_POSTCONDITION","setup":"Provider click response alone produces completed_verified.","assertions":["fresh postcondition evidence required"]},{"id":"S16_VALID_FALLBACK_LOWER_ASSURANCE","expected":"valid","setup":"Semantic method unavailable; policy-approved keyboard fallback is used and assurance is lowered.","assertions":["fallback explicit","limitations retained"]},{"id":"S17_INVALID_HIDDEN_COORDINATE_FALLBACK","expected":"invalid","expected_code":"SEMANTIC_HIDDEN_FALLBACK","setup":"Automation silently falls back to screen coordinates.","assertions":["policy/assurance disclosure required"]},{"id":"S18_VALID_UNCERTAIN_ACTION_RECOVERY","expected":"valid","setup":"Disconnect after input makes effect uncertain; fresh state is reacquired before deciding retry.","assertions":["no blind retry","new Attempt if retried"]},{"id":"S19_INVALID_BLIND_ACTION_RETRY","expected":"invalid","expected_code":"SEMANTIC_EFFECT_UNRECONCILED","setup":"Action automatically retries after uncertain effect.","assertions":["reconciliation required"]},{"id":"S20_VALID_VISUAL_EVIDENCE_REDACTION","expected":"valid","setup":"Before/after target-region evidence is redacted under privacy policy.","assertions":["Object/Artifact retained","redaction refs present"]},{"id":"S21_INVALID_PRIVATE_TEXT_PUBLIC","expected":"invalid","expected_code":"SEMANTIC_PRIVATE_DATA_EXPORT_PROHIBITED","setup":"Password/clipboard/private semantic value appears in public evidence.","assertions":["reject/redact/security path"]},{"id":"H01_VALID_SHELL_ATTACH","expected":"valid","setup":"Shell Client attaches to Workspace with immutable Layout Revision and current Projections.","assertions":["runtime truth external","permissions exact"]},{"id":"H02_INVALID_SHELL_DISCONNECT_STOPS_RUNTIME","expected":"invalid","expected_code":"SHELL_DISCONNECT_NOT_RUNTIME_STOP","setup":"Mobile client disconnect automatically stops Application/Browser/Transfer work.","assertions":["separate authorized stop required"]},{"id":"H03_VALID_PANEL_BINDING","expected":"valid","setup":"Panel binds to exact runtime/source entities under observe/control permissions.","assertions":["Binding separate from Panel"]},{"id":"H04_INVALID_PANEL_STATE_AS_RUNTIME_STATE","expected":"invalid","expected_code":"SHELL_PRESENTATION_NOT_RUNTIME_TRUTH","setup":"Panel closed/hidden is treated as Process/Activity stopped.","assertions":["runtime record unchanged"]},{"id":"H05_VALID_LAYOUT_REVISION","expected":"valid","setup":"Desktop Layout Revision is immutable and placements reference Panels.","assertions":["new revision for changes"]},{"id":"H06_VALID_PHONE_RESPONSIVE_PROJECTION","expected":"valid","setup":"Phone viewport derives single-primary switcher projection from desktop Layout Revision.","assertions":["desktop revision unchanged","derived_only true"]},{"id":"H07_INVALID_VIEWPORT_MUTATES_LAYOUT","expected":"invalid","expected_code":"RESPONSIVE_PROJECTION_MUTATES_LAYOUT","setup":"Opening phone client rewrites canonical desktop Layout Revision.","assertions":["responsive projection required"]},{"id":"H08_VALID_LOW_BANDWIDTH_DEGRADATION","expected":"valid","setup":"Client Observation causes reduced video/update frequency while runtime continues.","assertions":["presentation-only degradation"]},{"id":"H09_INVALID_STALE_PROJECTION_COMMAND","expected":"invalid","expected_code":"SHELL_PROJECTION_STALE","setup":"Command is issued from stale Projection/source revision without refresh.","assertions":["fresh source/permission check required"]},{"id":"H10_VALID_HUMAN_TAKEOVER","expected":"valid","setup":"Control Transfer quiesces automation, revokes old fence, issues human Lease/fence.","assertions":["old automation fenced","new authority verified"]},{"id":"H11_INVALID_SPLIT_CONTROL","expected":"invalid","expected_code":"SHELL_CONTROL_SPLIT_BRAIN","setup":"Human and automation can both mutate under valid-looking stale fences.","assertions":["all mutation blocked until reconciliation"]},{"id":"H12_VALID_RETURN_TO_AUTOMATION","expected":"valid","setup":"Human completes challenge then transfers control back with return conditions and fresh automation fence.","assertions":["new Lease/fence","state reacquired"]},{"id":"H13_INVALID_CONTROL_TRANSFER_WITH_PENDING_INPUT","expected":"invalid","expected_code":"CONTROL_TRANSFER_NOT_QUIESCED","setup":"Control transfers while old holder has unresolved input/effects.","assertions":["quiesce/reconcile required"]},{"id":"H14_VALID_KEYBOARD_ACCESSIBILITY","expected":"valid","setup":"All primary Shell/Panel operations are reachable by keyboard with semantic labels/focus order.","assertions":["accessibility requirement satisfied"]},{"id":"H15_INVALID_TOUCH_ONLY_CONTROL","expected":"invalid","expected_code":"SHELL_KEYBOARD_ACCESSIBILITY_MISSING","setup":"Critical panel action is touch-only without semantic/keyboard equivalent.","assertions":["blocked from conformance"]},{"id":"H16_VALID_TEXT_SCALING_REFLOW","expected":"valid","setup":"Large text and narrow viewport reflow without hiding critical controls.","assertions":["responsive/accessibility projection passes"]},{"id":"H17_INVALID_COLOR_ONLY_STATUS","expected":"invalid","expected_code":"SHELL_STATUS_COLOR_ONLY","setup":"Activity/health status is conveyed only by color.","assertions":["semantic text/icon required"]},{"id":"H18_VALID_RTL_LOCALIZATION","expected":"valid","setup":"RTL/localized labels preserve logical order, commands and evidence references.","assertions":["identity unaffected"]},{"id":"H19_INVALID_PUBLIC_CLIENT_CACHE","expected":"invalid","expected_code":"SHELL_PRIVATE_CACHE_EXPORT_PROHIBITED","setup":"Private profile/clipboard/screenshot cache is exported publicly.","assertions":["privacy/redaction required"]},{"id":"X01_VALID_BROWSER_BACKEND_REPLACEMENT","expected":"valid","setup":"Playwright/CDP backend is replaced by another Browser Provider.","assertions":["Binary/Profile stable","new Process/Context/Page/semantic generations"]},{"id":"X02_VALID_APPLICATION_BACKEND_REPLACEMENT","expected":"valid","setup":"Application runtime moves from local native to VM/remote Provider.","assertions":["Application identity stable","new Compatibility/Session/Process/Recovery Verification"]},{"id":"X03_VALID_SEMANTIC_PROVIDER_REPLACEMENT","expected":"valid","setup":"Accessibility semantic Provider is replaced by DOM/platform adapter.","assertions":["Selector/Target stable","new Context/Snapshot/Target Result","assurance explicit"]},{"id":"X04_VALID_SHELL_FRAMEWORK_REPLACEMENT","expected":"valid","setup":"Shell UI framework changes while Panel Types, Layout Revisions and runtime truth remain stable.","assertions":["presentation migration explicit"]},{"id":"X05_INVALID_NEGATIVE_HISTORY_DELETE","expected":"invalid","expected_code":"WP09_NEGATIVE_EVIDENCE_IMMUTABLE","setup":"Stale/ambiguous/challenged/failed records are deleted to present success.","assertions":["history retained"]}]}