{"$schema":"https://json-schema.org/draft/2020-12/schema","$id":"urn:ptah:schema:security:reproduction-protocol:0.1.0","title":"Ptah Security Reproduction Protocol","x-ptah-schema-name":"security.reproduction-protocol","x-ptah-schema-version":"0.1.0","x-ptah-maturity":"candidate","type":"object","additionalProperties":false,"required":["envelope","protocol_key","claim_scope","required_inputs","environment_requirements","independence_requirements","success_criteria","failure_criteria","created_at","extensions"],"properties":{"envelope":{"allOf":[{"$ref":"urn:ptah:schema:common:entity-envelope:0.1.0"},{"properties":{"entity_kind":{"const":"security.reproduction_protocol"}}}]},"protocol_key":{"type":"string"},"claim_scope":{"type":"array","items":{"type":"string"}},"required_inputs":{"type":"array","items":{"type":"string"}},"environment_requirements":{"type":"object"},"independence_requirements":{"type":"array","items":{"type":"string"}},"success_criteria":{"type":"array","items":{"type":"string"}},"failure_criteria":{"type":"array","items":{"type":"string"}},"created_at":{"$ref":"urn:ptah:schema:common:definitions:0.1.0#/$defs/utcDateTime"},"extensions":{"$ref":"urn:ptah:schema:common:definitions:0.1.0#/$defs/extensions"}}}