{"state_machine_name":"application.session.lifecycle","state_machine_version":"0.1.0","subject_entity_kinds":["application.session"],"states":[{"name":"preparing","terminal":false,"description":"Exact installation, Provider and execution context are being prepared.","proof_dimension":"lifecycle","entry_requirements":["Compatibility and new Attempt exist."]},{"name":"running","terminal":false,"description":"At least one current runtime Process is active.","proof_dimension":"lifecycle","entry_requirements":["Process and readiness evidence exist."]},{"name":"degraded","terminal":false,"description":"Only bounded headless/display/semantic scope is available.","proof_dimension":"lifecycle","entry_requirements":["Availability limitations exist."]},{"name":"detached","terminal":false,"description":"No Shell client is attached while runtime remains active.","proof_dimension":"lifecycle","entry_requirements":["Runtime liveness evidence exists."]},{"name":"checkpointing","terminal":false,"description":"Application checkpoint components are being captured.","proof_dimension":"lifecycle","entry_requirements":["Checkpoint Request exists."]},{"name":"recovering","terminal":false,"description":"A restored/new runtime generation is under functional verification.","proof_dimension":"lifecycle","entry_requirements":["Restore/Recovery Activities exist."]},{"name":"stopped","terminal":true,"description":"Runtime stopped and cleanup is verified.","proof_dimension":"lifecycle","entry_requirements":["Process termination and cleanup evidence exist."]},{"name":"failed","terminal":true,"description":"Session ended with retained failure/partial effects.","proof_dimension":"lifecycle","entry_requirements":["Failure evidence exists."]},{"name":"uncertain","terminal":false,"description":"Runtime/external effects are unresolved.","proof_dimension":"lifecycle","entry_requirements":["Reconciliation required."]}],"initial_states":["preparing"],"transitions":[{"transition_name":"create","from_states":[null],"to_state":"preparing","transition_class":"normal","authority_classes":["ptah_control_plane"],"side_effecting":true,"required_preconditions":["Exact current context and new Attempt exist."],"required_evidence_kinds":["receipt","attempt","compatibility"],"required_receipt_proof_levels":["dispatched"]},{"transition_name":"mark_running","from_states":["preparing","recovering","degraded","detached"],"to_state":"running","transition_class":"normal","authority_classes":["provider","ptah_control_plane","verifier"],"side_effecting":false,"required_preconditions":["Current Process and application readiness are proven."],"required_evidence_kinds":["receipt","verification"],"required_receipt_proof_levels":["output_verified"]},{"transition_name":"degrade","from_states":["preparing","running","detached","recovering"],"to_state":"degraded","transition_class":"normal","authority_classes":["provider","ptah_control_plane"],"side_effecting":false,"required_preconditions":["Bounded available scope is explicit."],"required_evidence_kinds":["receipt","health_observation"],"required_receipt_proof_levels":[]},{"transition_name":"detach","from_states":["running","degraded"],"to_state":"detached","transition_class":"normal","authority_classes":["shell_client","ptah_control_plane"],"side_effecting":false,"required_preconditions":["Runtime remains active."],"required_evidence_kinds":["receipt"],"required_receipt_proof_levels":[]},{"transition_name":"checkpoint","from_states":["running","degraded","detached"],"to_state":"checkpointing","transition_class":"normal","authority_classes":["workspace_owner","ptah_control_plane"],"side_effecting":true,"required_preconditions":["Checkpoint Request and backend capability exist."],"required_evidence_kinds":["receipt","checkpoint_request"],"required_receipt_proof_levels":["accepted"]},{"transition_name":"recover","from_states":["preparing","checkpointing","uncertain"],"to_state":"recovering","transition_class":"recovery","authority_classes":["ptah_control_plane","provider"],"side_effecting":true,"required_preconditions":["New generation and Recovery Verification plan exist."],"required_evidence_kinds":["receipt","restore_run","attempt"],"required_receipt_proof_levels":["dispatched"]},{"transition_name":"stop","from_states":["preparing","running","degraded","detached","checkpointing","recovering","uncertain"],"to_state":"stopped","transition_class":"cancellation","authority_classes":["caller","workspace_owner","ptah_control_plane","provider"],"side_effecting":true,"required_preconditions":["Stop and cleanup evidence exist."],"required_evidence_kinds":["receipt","reconciliation"],"required_receipt_proof_levels":["operation_completed"]},{"transition_name":"fail","from_states":["preparing","running","degraded","detached","checkpointing","recovering","uncertain"],"to_state":"failed","transition_class":"failure","authority_classes":["provider","ptah_control_plane","verifier"],"side_effecting":false,"required_preconditions":["Failure and cleanup/recovery disposition exist."],"required_evidence_kinds":["receipt","error","reconciliation"],"required_receipt_proof_levels":["operation_completed"]},{"transition_name":"mark_uncertain","from_states":["preparing","running","checkpointing","recovering"],"to_state":"uncertain","transition_class":"recovery","authority_classes":["provider","ptah_control_plane"],"side_effecting":false,"required_preconditions":["Runtime/external effect is unresolved."],"required_evidence_kinds":["receipt","reconciliation"],"required_receipt_proof_levels":["operation_completed"]}],"unknown_state_policy":"reject","migration_policy":{"state_mapping_required_for_breaking_change":true,"unmapped_state_behavior":"manual_review","migration_definition_refs":[]},"extensions":{}}